sugarpy/__init__.py
sugarpy/claucy/__init__.py
sugarpy/claucy/claucy.py
sugarpy/config.py
sugarpy/enum.py
sugarpy/metrics.py
sugarpy/morphemes/__init__.py
sugarpy/morphemes/morphemes.py
sugarpy/morphemes/rules.py
sugarpy/morphemes/utils.py
sugarpy/norms.py
sugarpy/sentences/__init__.py
sugarpy/sentences/sentences.py
sugar_python-0.4.2.dist-info/LICENSE
sugar_python-0.4.2.dist-info/METADATA
sugar_python-0.4.2.dist-info/WHEEL
sugar_python-0.4.2.dist-info/RECORD
