Metadata-Version: 2.3
Name: sugar-python
Version: 0.4.2
Summary: SUGAR metrics in python
License: MIT
Author: George D. Torres
Requires-Python: >=3.9,<4.0
Classifier: License :: OSI Approved :: MIT License
Classifier: Programming Language :: Python :: 3
Classifier: Programming Language :: Python :: 3.9
Classifier: Programming Language :: Python :: 3.10
Classifier: Programming Language :: Python :: 3.11
Classifier: Programming Language :: Python :: 3.12
Classifier: Programming Language :: Python :: 3.13
Requires-Dist: lemminflect (>=0.2.3,<0.3.0)
Requires-Dist: nltk (>=3.8.1,<4.0.0)
Requires-Dist: pylcs (>=0.1.1,<0.2.0)
Requires-Dist: spacy (>=3.7.2,<4.0.0)
